owlracle_python/__init__.py
owlracle_python/owlracle.py
owlracle_python-0.1.1.dist-info/LICENSE.md
owlracle_python-0.1.1.dist-info/METADATA
owlracle_python-0.1.1.dist-info/WHEEL
owlracle_python-0.1.1.dist-info/RECORD
