Metadata-Version: 2.1
Name: owlracle-python
Version: 0.1.1
Summary: A simple Python API wrapper for Owlracle
Home-page: https://github.com/alb2001/owlracle-python
License: MIT
Keywords: owlracle,api,wrapper,blockchain,gas,oracle
Author: alb2001
Author-email: alb2001@outlook.es
Requires-Python: >=3.9,<4.0
Classifier: License :: OSI Approved :: MIT License
Classifier: Programming Language :: Python :: 3
Classifier: Programming Language :: Python :: 3.9
Classifier: Programming Language :: Python :: 3.10
Classifier: Programming Language :: Python :: 3.11
Classifier: Programming Language :: Python :: 3.12
Requires-Dist: requests (>=2.31.0,<3.0.0)
Project-URL: Repository, https://github.com/alb2001/owlracle-python
